LICENSE
MANIFEST.in
README.md
requirements.txt
setup.cfg
setup.py
event_signal/__init__.py
event_signal/__version__.py
event_signal/binder.py
event_signal/interface.py
event_signal/method_observer_metaclass.py
event_signal/qt_binder.py
event_signal/signal_qt.py
event_signal/signaler.py
event_signal/signaler_prop.py
event_signal.egg-info/PKG-INFO
event_signal.egg-info/SOURCES.txt
event_signal.egg-info/dependency_links.txt
event_signal.egg-info/requires.txt
event_signal.egg-info/top_level.txt