Metadata-Version: 1.1
Name: event-signal
Version: 1.8.0
Summary: Library to help notify when something has changed.
Home-page: https://github.com/justengel/event_signal
Author: Justin Engel
Author-email: jtengel08@gmail.com
License: MIT
Download-URL: https://github.com/justengel/event_signal/archive/v1.8.0.tar.gz
Keywords: signal observer signaler event javascript events bind
Platform: any
Classifier: Programming Language :: Python
Classifier: Programming Language :: Python :: 3
Classifier: Operating System :: OS Independent
